ktoolkits/__init__.py
ktoolkits/formatting_utils.py
ktoolkits/version.py
ktoolkits/agent/__init__.py
ktoolkits/agent/agent_chat.py
ktoolkits/agent/async_runner.py
ktoolkits/agent/function_call.py
ktoolkits/agent/runner.py
ktoolkits/api_entities/__init__.py
ktoolkits/api_entities/base_request.py
ktoolkits/api_entities/http_request.py
ktoolkits/api_entities/ktool_response.py
ktoolkits/client/__init__.py
ktoolkits/client/base_api.py
ktoolkits/common/__init__.py
ktoolkits/common/api_key.py
ktoolkits/common/constants.py
ktoolkits/common/env.py
ktoolkits/common/error.py
ktoolkits/common/logging.py
ktoolkits/common/utils.py
ktoolkits/io/__init__.py
ktoolkits/io/base.py
ktoolkits/io/console.py
ktoolkits/io/websockets.py
ktoolkits-0.0.3.dist-info/METADATA
ktoolkits-0.0.3.dist-info/WHEEL
ktoolkits-0.0.3.dist-info/top_level.txt
ktoolkits-0.0.3.dist-info/RECORD
